Metadata-Version: 2.1
Name: mypythonlib-nini
Version: 0.0.1
Summary: sipmle square calculator
Home-page: UNKNOWN
Author: nini pruidze
License: MIT
Keywords: mypythonlib_nini
Platform: UNKNOWN
License-File: LICENCE.txt
